{
  "Category": {
    "0": "Alpine.js",
    "1": "Alpine.js",
    "2": "Alpine.js",
    "3": "Alpine.js",
    "4": "Alpine.js",
    "5": "Alpine.js",
    "6": "Alpine.js",
    "7": "Alpine.js",
    "8": "Alpine.js",
    "9": "Alpine.js",
    "10": "Alpine.js",
    "11": "Alpine.js",
    "12": "Alpine.js"
  },
  "Titles": {
    "0": "Build a Livewire Drag & Drop Uploader",
    "1": "Build a Notes App with Alpine.js",
    "2": "Alpine Store Basics",
    "3": "Learn Alpine.js",
    "4": "Meilisearch Instant Search with Alpine.js",
    "5": "Global Modals with Livewire and Alpine.js",
    "6": "Livewire Infinite Scroll",
    "7": "Alpine.js Auto Textarea Height",
    "8": "Crop and Upload Avatars with Laravel Livewire",
    "9": "Instantsearch with TNTSearch and Alpine.js",
    "10": "Build a Multi-room Realtime Chat with Livewire",
    "11": "Alpine.js State Management with Spruce",
    "12": "Build an RSS reader with Alpine.js"
  },
  "Duration": {
    "0": " 43 mins",
    "1": " 55 mins",
    "2": " 29 mins",
    "3": "2 hrs 10 mins",
    "4": " 42 mins",
    "5": " 18 mins",
    "6": " 34 mins",
    "7": " 6 mins",
    "8": " 25 mins",
    "9": " 53 mins",
    "10": "1 hr 23 mins",
    "11": " 9 mins",
    "12": " 14 mins"
  },
  "Episodes": {
    "0": " 9 episodes",
    "1": " 11 episodes",
    "2": " 5 episodes",
    "3": " 19 episodes",
    "4": " 12 episodes",
    "5": " 1 episode",
    "6": " 8 episodes",
    "7": " 1 episode",
    "8": " 7 episodes",
    "9": " 9 episodes",
    "10": " 11 episodes",
    "11": " 5 episodes",
    "12": " 1 episode"
  },
  "Links": {
    "0": "https:\/\/codecourse.com\/courses\/build-a-livewire-drag-drop-uploader",
    "1": "https:\/\/codecourse.com\/courses\/build-a-notes-app-with-alpine-js",
    "2": "https:\/\/codecourse.com\/courses\/alpine-store-basics",
    "3": "https:\/\/codecourse.com\/courses\/learn-alpine-js",
    "4": "https:\/\/codecourse.com\/courses\/meilisearch-instant-search-with-alpine-js",
    "5": "https:\/\/codecourse.com\/courses\/global-modals-with-livewire",
    "6": "https:\/\/codecourse.com\/courses\/livewire-infinite-scroll",
    "7": "https:\/\/codecourse.com\/courses\/alpine.js-auto-textarea-height",
    "8": "https:\/\/codecourse.com\/courses\/crop-and-upload-avatars-with-laravel-livewire",
    "9": "https:\/\/codecourse.com\/courses\/instantsearch-with-tntsearch-and-alpine-js",
    "10": "https:\/\/codecourse.com\/courses\/build-a-multi-room-realtime-chat-with-livewire",
    "11": "https:\/\/codecourse.com\/courses\/alpine-js-state-management-with-spruce",
    "12": "https:\/\/codecourse.com\/courses\/build-an-rss-reader-with-alpine-js"
  }
}